savageml/__init__.py
savageml/validation.py
savageml/version.py
savageml/models/__init__.py
savageml/models/base_model.py
savageml/models/layerless_dense_net_model.py
savageml/models/layerless_sparse_net_model.py
savageml/models/matix_net_model.py
savageml/simulations/__init__.py
savageml/simulations/base_simulation.py
savageml/simulations/binary_and_simulation.py
savageml/simulations/binary_or_simulation.py
savageml/simulations/binary_reflexive_simulation.py
savageml/simulations/binary_xor_simulation.py
savageml/simulations/simulation_state.py
SavageML-0.2.1.dist-info/LICENSE
SavageML-0.2.1.dist-info/METADATA
SavageML-0.2.1.dist-info/WHEEL
SavageML-0.2.1.dist-info/top_level.txt
SavageML-0.2.1.dist-info/RECORD
